spectrum_plotter/__init__.py
spectrum_plotter/core.py
spectrum_plotter-0.2.3.dist-info/LICENSE
spectrum_plotter-0.2.3.dist-info/METADATA
spectrum_plotter-0.2.3.dist-info/WHEEL
spectrum_plotter-0.2.3.dist-info/top_level.txt
spectrum_plotter-0.2.3.dist-info/RECORD
