Metadata-Version: 2.1
Name: spectrum-plotter
Version: 0.2.3
Summary: A Python package for creating publication quality plots for neutron / photon / particle spectrum 
Home-page: https://github.com/fusion-energy/spectrum_plotter
Author: The Spectrum Plotter Development Team
Author-email: mail@jshimwell.com
License: UNKNOWN
Platform: UNKNOWN
Classifier: Natural Language :: English
Classifier: Topic :: Scientific/Engineering
Classifier: Programming Language :: Python :: 3
Classifier: Programming Language :: Python :: 3.6
Classifier: Programming Language :: Python :: 3.7
Classifier: Programming Language :: Python :: 3.8
Classifier: Programming Language :: Python :: 3.9
Classifier: License :: OSI Approved :: MIT License
Classifier: Operating System :: OS Independent
Requires-Python: >=3.6
License-File: LICENSE
Requires-Dist: numpy (>=1.9)
Requires-Dist: matplotlib (>=3.2.2)
Requires-Dist: plotly
Requires-Dist: openmc-tally-unit-converter
